typeany/__init__.py
typeany-0.1.0.dist-info/WHEEL
typeany-0.1.0.dist-info/METADATA
typeany-0.1.0.dist-info/RECORD
