Metadata-Version: 2.1
Name: typeany
Version: 0.1.0
Summary: Preserving a cool name for Pythonn library for anytype.io. type[Any].
License: MIT
Author: Bobronium
Author-email: appkiller16@gmail.com
Requires-Python: >=3.10,<4.0
Classifier: License :: OSI Approved :: MIT License
Classifier: Programming Language :: Python :: 3
Classifier: Programming Language :: Python :: 3.10
